[
{
  "model": "categories.pool",
  "pk": "BMO_1",
  "fields": {
    "name": "HVAC Mainentance",
    "number": "1",
    "vehicle": "BMO",
    "threshold": "$15 million",
    "naics": [
      43
    ]
  }
},
{
  "model": "categories.pool",
  "pk": "BMO_10",
  "fields": {
    "name": "Building Management Services",
    "number": "10",
    "vehicle": "BMO",
    "threshold": "$7.5 million",
    "naics": [
      47
    ]
  }
},
{
  "model": "categories.pool",
  "pk": "BMO_11",
  "fields": {
    "name": "Architectural and Framework Building Maintenance Services",
    "number": "11",
    "vehicle": "BMO",
    "threshold": "$36.5 million",
    "naics": [
      40
    ]
  }
},
{
  "model": "categories.pool",
  "pk": "BMO_12",
  "fields": {
    "name": "Commissioning Services",
    "number": "12",
    "vehicle": "BMO",
    "threshold": "$15 million",
    "naics": [
      48
    ]
  }
},
{
  "model": "categories.pool",
  "pk": "BMO_13",
  "fields": {
    "name": "Elevator Inspection Services",
    "number": "13",
    "vehicle": "BMO",
    "threshold": "$7.5 million",
    "naics": [
      49
    ]
  }
},
{
  "model": "categories.pool",
  "pk": "BMO_14",
  "fields": {
    "name": "Other Facility Management Related Services",
    "number": "14",
    "vehicle": "BMO",
    "threshold": "$38.5 million",
    "naics": [
      39
    ]
  }
},
{
  "model": "categories.pool",
  "pk": "BMO_15",
  "fields": {
    "name": "Pest Control",
    "number": "15",
    "vehicle": "BMO",
    "threshold": "$11 million",
    "naics": [
      51
    ]
  }
},
{
  "model": "categories.pool",
  "pk": "BMO_16",
  "fields": {
    "name": "Waste Management and Recycling Services",
    "number": "16",
    "vehicle": "BMO",
    "threshold": "$38.5 million",
    "naics": [
      55
    ]
  }
},
{
  "model": "categories.pool",
  "pk": "BMO_17",
  "fields": {
    "name": "Cemetery Maintenance",
    "number": "17",
    "vehicle": "BMO",
    "threshold": "$7.5 million",
    "naics": [
      54
    ]
  }
},
{
  "model": "categories.pool",
  "pk": "BMO_2",
  "fields": {
    "name": "Plumbing and Pipefitting",
    "number": "2",
    "vehicle": "BMO",
    "threshold": "$15 million",
    "naics": [
      44
    ]
  }
},
{
  "model": "categories.pool",
  "pk": "BMO_3",
  "fields": {
    "name": "Elevator Maintenance",
    "number": "3",
    "vehicle": "BMO",
    "threshold": "$7.5 million",
    "naics": [
      46
    ]
  }
},
{
  "model": "categories.pool",
  "pk": "BMO_4",
  "fields": {
    "name": "Electrical Maintenance",
    "number": "4",
    "vehicle": "BMO",
    "threshold": "$15 million",
    "naics": [
      42
    ]
  }
},
{
  "model": "categories.pool",
  "pk": "BMO_5",
  "fields": {
    "name": "Janitorial",
    "number": "5",
    "vehicle": "BMO",
    "threshold": "$18 million",
    "naics": [
      52
    ]
  }
},
{
  "model": "categories.pool",
  "pk": "BMO_6",
  "fields": {
    "name": "Landscaping / Grounds Maintenance",
    "number": "6",
    "vehicle": "BMO",
    "threshold": "$7.5 million",
    "naics": [
      53
    ]
  }
},
{
  "model": "categories.pool",
  "pk": "BMO_7",
  "fields": {
    "name": "Fire Alarm System Maintenance and Repair",
    "number": "7",
    "vehicle": "BMO",
    "threshold": "$20.5 million",
    "naics": [
      50
    ]
  }
},
{
  "model": "categories.pool",
  "pk": "BMO_8",
  "fields": {
    "name": "Fire Supression System Preventative Maintenance and Repair Services",
    "number": "8",
    "vehicle": "BMO",
    "threshold": "$15 million",
    "naics": [
      45
    ]
  }
},
{
  "model": "categories.pool",
  "pk": "BMO_9",
  "fields": {
    "name": "Roofing Services",
    "number": "9",
    "vehicle": "BMO",
    "threshold": "$15 million",
    "naics": [
      41
    ]
  }
},
{
  "model": "categories.pool",
  "pk": "BMO_SB_1",
  "fields": {
    "name": "HVAC Mainentance",
    "number": "1",
    "vehicle": "BMO_SB",
    "threshold": "$15 million",
    "naics": [
      43
    ]
  }
},
{
  "model": "categories.pool",
  "pk": "BMO_SB_10",
  "fields": {
    "name": "Building Management Services",
    "number": "10",
    "vehicle": "BMO_SB",
    "threshold": "$7.5 million",
    "naics": [
      47
    ]
  }
},
{
  "model": "categories.pool",
  "pk": "BMO_SB_11",
  "fields": {
    "name": "Architectural and Framework Building Maintenance Services",
    "number": "11",
    "vehicle": "BMO_SB",
    "threshold": "$36.5 million",
    "naics": [
      40
    ]
  }
},
{
  "model": "categories.pool",
  "pk": "BMO_SB_12",
  "fields": {
    "name": "Commissioning Services",
    "number": "12",
    "vehicle": "BMO_SB",
    "threshold": "$15 million",
    "naics": [
      48
    ]
  }
},
{
  "model": "categories.pool",
  "pk": "BMO_SB_13",
  "fields": {
    "name": "Elevator Inspection Services",
    "number": "13",
    "vehicle": "BMO_SB",
    "threshold": "$7.5 million",
    "naics": [
      49
    ]
  }
},
{
  "model": "categories.pool",
  "pk": "BMO_SB_14",
  "fields": {
    "name": "Other Facility Management Related Services",
    "number": "14",
    "vehicle": "BMO_SB",
    "threshold": "$38.5 million",
    "naics": [
      39
    ]
  }
},
{
  "model": "categories.pool",
  "pk": "BMO_SB_15",
  "fields": {
    "name": "Pest Control",
    "number": "15",
    "vehicle": "BMO_SB",
    "threshold": "$11 million",
    "naics": [
      51
    ]
  }
},
{
  "model": "categories.pool",
  "pk": "BMO_SB_16",
  "fields": {
    "name": "Waste Management and Recycling Services",
    "number": "16",
    "vehicle": "BMO_SB",
    "threshold": "$38.5 million",
    "naics": [
      55
    ]
  }
},
{
  "model": "categories.pool",
  "pk": "BMO_SB_17",
  "fields": {
    "name": "Cemetery Maintenance",
    "number": "17",
    "vehicle": "BMO_SB",
    "threshold": "$7.5 million",
    "naics": [
      54
    ]
  }
},
{
  "model": "categories.pool",
  "pk": "BMO_SB_2",
  "fields": {
    "name": "Plumbing and Pipefitting",
    "number": "2",
    "vehicle": "BMO_SB",
    "threshold": "$15 million",
    "naics": [
      44
    ]
  }
},
{
  "model": "categories.pool",
  "pk": "BMO_SB_3",
  "fields": {
    "name": "Elevator Maintenance",
    "number": "3",
    "vehicle": "BMO_SB",
    "threshold": "$7.5 million",
    "naics": [
      46
    ]
  }
},
{
  "model": "categories.pool",
  "pk": "BMO_SB_4",
  "fields": {
    "name": "Electrical Maintenance",
    "number": "4",
    "vehicle": "BMO_SB",
    "threshold": "$15 million",
    "naics": [
      42
    ]
  }
},
{
  "model": "categories.pool",
  "pk": "BMO_SB_5",
  "fields": {
    "name": "Janitorial",
    "number": "5",
    "vehicle": "BMO_SB",
    "threshold": "$18 million",
    "naics": [
      52
    ]
  }
},
{
  "model": "categories.pool",
  "pk": "BMO_SB_6",
  "fields": {
    "name": "Landscaping / Grounds Maintenance",
    "number": "6",
    "vehicle": "BMO_SB",
    "threshold": "$7.5 million",
    "naics": [
      53
    ]
  }
},
{
  "model": "categories.pool",
  "pk": "BMO_SB_7",
  "fields": {
    "name": "Fire Alarm System Maintenance and Repair",
    "number": "7",
    "vehicle": "BMO_SB",
    "threshold": "$20.5 million",
    "naics": [
      50
    ]
  }
},
{
  "model": "categories.pool",
  "pk": "BMO_SB_8",
  "fields": {
    "name": "Fire Supression System Preventative Maintenance and Repair Services",
    "number": "8",
    "vehicle": "BMO_SB",
    "threshold": "$15 million",
    "naics": [
      45
    ]
  }
},
{
  "model": "categories.pool",
  "pk": "BMO_SB_9",
  "fields": {
    "name": "Roofing Services",
    "number": "9",
    "vehicle": "BMO_SB",
    "threshold": "$15 million",
    "naics": [
      41
    ]
  }
},
{
  "model": "categories.pool",
  "pk": "HCATS_1",
  "fields": {
    "name": "HCATS Unrestricted Pool 1",
    "number": "1",
    "vehicle": "HCATS",
    "threshold": "$11 million",
    "naics": [
      35,
      36,
      37
    ]
  }
},
{
  "model": "categories.pool",
  "pk": "HCATS_2",
  "fields": {
    "name": "HCATS Unrestricted Pool 2",
    "number": "2",
    "vehicle": "HCATS",
    "threshold": "$15 million",
    "naics": [
      5,
      6,
      7,
      9,
      38
    ]
  }
},
{
  "model": "categories.pool",
  "pk": "HCATS_SB_1",
  "fields": {
    "name": "HCATS Small Business Pool 1",
    "number": "1",
    "vehicle": "HCATS_SB",
    "threshold": "$11 million",
    "naics": [
      35,
      36,
      37
    ]
  }
},
{
  "model": "categories.pool",
  "pk": "HCATS_SB_2",
  "fields": {
    "name": "HCATS Small Business Pool 2",
    "number": "2",
    "vehicle": "HCATS_SB",
    "threshold": "$15 million",
    "naics": [
      5,
      6,
      7,
      9,
      38
    ]
  }
},
{
  "model": "categories.pool",
  "pk": "OASIS_1",
  "fields": {
    "name": "Management, Scientific, and Technical Services",
    "number": "1",
    "vehicle": "OASIS",
    "threshold": "$14 million",
    "naics": [
      1,
      2,
      3,
      4,
      5,
      6,
      7,
      8,
      9,
      10,
      11,
      12,
      13,
      14,
      15,
      16,
      17,
      18,
      19,
      20,
      21
    ]
  }
},
{
  "model": "categories.pool",
  "pk": "OASIS_2",
  "fields": {
    "name": "Financial and Accounting Services",
    "number": "2",
    "vehicle": "OASIS",
    "threshold": "$19 million",
    "naics": [
      22,
      23,
      24,
      25,
      26
    ]
  }
},
{
  "model": "categories.pool",
  "pk": "OASIS_3",
  "fields": {
    "name": "Military, Marine, and Energy Engineering",
    "number": "3",
    "vehicle": "OASIS",
    "threshold": "$35.5 million",
    "naics": [
      27,
      28,
      29
    ]
  }
},
{
  "model": "categories.pool",
  "pk": "OASIS_4",
  "fields": {
    "name": "Scientific Research and Development",
    "number": "4",
    "vehicle": "OASIS",
    "threshold": "500 employee",
    "naics": [
      30,
      31
    ]
  }
},
{
  "model": "categories.pool",
  "pk": "OASIS_5A",
  "fields": {
    "name": "Aircraft Parts and Engines Research and Development",
    "number": "5A",
    "vehicle": "OASIS",
    "threshold": "1000 employee",
    "naics": [
      32
    ]
  }
},
{
  "model": "categories.pool",
  "pk": "OASIS_5B",
  "fields": {
    "name": "Space and Missiles Research and Development",
    "number": "5B",
    "vehicle": "OASIS",
    "threshold": "1000 employee",
    "naics": [
      33
    ]
  }
},
{
  "model": "categories.pool",
  "pk": "OASIS_6",
  "fields": {
    "name": "Aircraft Research and Development",
    "number": "6",
    "vehicle": "OASIS",
    "threshold": "1500 employee",
    "naics": [
      34
    ]
  }
},
{
  "model": "categories.pool",
  "pk": "OASIS_SB_1",
  "fields": {
    "name": "Management, Scientific, and Technical Services",
    "number": "1",
    "vehicle": "OASIS_SB",
    "threshold": "$14 million",
    "naics": [
      1,
      2,
      3,
      4,
      5,
      6,
      7,
      8,
      9,
      10,
      11,
      12,
      13,
      14,
      15,
      16,
      17,
      18,
      19,
      20,
      21
    ]
  }
},
{
  "model": "categories.pool",
  "pk": "OASIS_SB_2",
  "fields": {
    "name": "Financial and Accounting Services",
    "number": "2",
    "vehicle": "OASIS_SB",
    "threshold": "$19 million",
    "naics": [
      22,
      23,
      24,
      25,
      26
    ]
  }
},
{
  "model": "categories.pool",
  "pk": "OASIS_SB_3",
  "fields": {
    "name": "Military, Marine, and Energy Engineering",
    "number": "3",
    "vehicle": "OASIS_SB",
    "threshold": "$35.5 million",
    "naics": [
      27,
      28,
      29
    ]
  }
},
{
  "model": "categories.pool",
  "pk": "OASIS_SB_4",
  "fields": {
    "name": "Scientific Research and Development",
    "number": "4",
    "vehicle": "OASIS_SB",
    "threshold": "500 employee",
    "naics": [
      30,
      31
    ]
  }
},
{
  "model": "categories.pool",
  "pk": "OASIS_SB_5A",
  "fields": {
    "name": "Aircraft Parts and Engines Research and Development",
    "number": "5A",
    "vehicle": "OASIS_SB",
    "threshold": "1000 employee",
    "naics": [
      32
    ]
  }
},
{
  "model": "categories.pool",
  "pk": "OASIS_SB_5B",
  "fields": {
    "name": "Space and Missiles Research and Development",
    "number": "5B",
    "vehicle": "OASIS_SB",
    "threshold": "1000 employee",
    "naics": [
      33
    ]
  }
},
{
  "model": "categories.pool",
  "pk": "OASIS_SB_6",
  "fields": {
    "name": "Aircraft Research and Development",
    "number": "6",
    "vehicle": "OASIS_SB",
    "threshold": "1500 employee",
    "naics": [
      34
    ]
  }
}
]
