[
{
  "model": "categories.zone",
  "pk": 1,
  "fields": {
    "states": [
      "VA",
      "MD",
      "DE",
      "PA",
      "NY",
      "NJ"
    ]
  }
},
{
  "model": "categories.zone",
  "pk": 2,
  "fields": {
    "states": [
      "RI",
      "CT",
      "NH",
      "ME",
      "VT",
      "MA"
    ]
  }
},
{
  "model": "categories.zone",
  "pk": 3,
  "fields": {
    "states": [
      "FL",
      "GA",
      "SC",
      "NC"
    ]
  }
},
{
  "model": "categories.zone",
  "pk": 4,
  "fields": {
    "states": [
      "OK",
      "TX"
    ]
  }
},
{
  "model": "categories.zone",
  "pk": 5,
  "fields": {
    "states": [
      "CA",
      "NV"
    ]
  }
},
{
  "model": "categories.zone",
  "pk": 6,
  "fields": {
    "states": [
      "KS",
      "IA",
      "IL",
      "MO",
      "NE"
    ]
  }
}
]
